[{"Events":13,"streets":[{"street":"hall road","date":"Tuesday, May 26, 2026"},{"street":"inglemire lane","date":"Tuesday, May 26, 2026"},{"street":"newbald grove","date":"Tuesday, May 26, 2026"},{"street":"beeford grove","date":"Tuesday, May 26, 2026"},{"street":"langtoft grove","date":"Tuesday, May 26, 2026"},{"street":"arram grove","date":"Tuesday, May 26, 2026"},{"street":"carnaby grove","date":"Tuesday, May 26, 2026"},{"street":"elm terrace","date":"Tuesday, May 26, 2026"},{"street":"elm street","date":"Tuesday, May 26, 2026"},{"street":"grantchester close","date":"Tuesday, May 26, 2026"},{"street":"huntley drive","date":"Tuesday, May 26, 2026"}]}]